qa_testing_one_of_sdk-1.2.1.dist-info/licenses/LICENSE
sampleapi/__init__.py
sampleapi/api_helper.py
sampleapi/configuration.py
sampleapi/sampleapi_client.py
sampleapi/controllers/__init__.py
sampleapi/controllers/api_controller.py
sampleapi/controllers/base_controller.py
sampleapi/exceptions/__init__.py
sampleapi/exceptions/api_exception.py
sampleapi/http/__init__.py
sampleapi/http/http_call_back.py
sampleapi/http/http_method_enum.py
sampleapi/http/http_request.py
sampleapi/http/http_response.py
sampleapi/models/__init__.py
sampleapi/models/details.py
sampleapi/models/item.py
sampleapi/models/items_request.py
sampleapi/models/items_response.py
sampleapi/models/pricing.py
sampleapi/models/pricing_1.py
sampleapi/models/pricing_2.py
sampleapi/models/pricing_3.py
sampleapi/models/pricing_4.py
sampleapi/models/pricing_5.py
sampleapi/models/pricing_6.py
sampleapi/models/pricing_77.py
sampleapi/models/specifications.py
sampleapi/models/status_enum.py
sampleapi/utilities/__init__.py
sampleapi/utilities/file_wrapper.py
sampleapi/utilities/union_type_lookup.py
qa_testing_one_of_sdk-1.2.1.dist-info/METADATA
qa_testing_one_of_sdk-1.2.1.dist-info/WHEEL
qa_testing_one_of_sdk-1.2.1.dist-info/top_level.txt
qa_testing_one_of_sdk-1.2.1.dist-info/RECORD
